README.rst
setup.py
seo_meow.egg-info/PKG-INFO
seo_meow.egg-info/SOURCES.txt
seo_meow.egg-info/dependency_links.txt
seo_meow.egg-info/top_level.txt
seomeow/__init__.py
seomeow/admin.py
seomeow/apps.py
seomeow/models.py
seomeow/migrations/0001_initial.py
seomeow/migrations/0002_auto_20160831_1214.py
seomeow/migrations/0003_auto_20160831_1249.py
seomeow/migrations/__init__.py
seomeow/templatetags/__init__.py
seomeow/templatetags/seomeow.py